README.md
printcolor.py
printcolor2.py
setup.py
printcolor.egg-info/PKG-INFO
printcolor.egg-info/SOURCES.txt
printcolor.egg-info/dependency_links.txt
printcolor.egg-info/top_level.txt