Metadata-Version: 2.1
Name: printcolor
Version: 1.2.0
Summary: print colorful string
Home-page: https://github.com/dustingo/PrintColor.git
Author: zack
Author-email: 514838728@qq.com
License: UNKNOWN
Platform: linux
